feagi_agent_webcam/__init__.py
feagi_agent_webcam/__main__.py
feagi_agent_webcam/configuration.py
feagi_agent_webcam/controller.py
feagi_agent_webcam-0.0.8.dist-info/LICENSE
feagi_agent_webcam-0.0.8.dist-info/METADATA
feagi_agent_webcam-0.0.8.dist-info/WHEEL
feagi_agent_webcam-0.0.8.dist-info/top_level.txt
feagi_agent_webcam-0.0.8.dist-info/RECORD
