Metadata-Version: 2.1
Name: feagi-agent-webcam
Version: 0.0.8
Summary: Feagi agent webcam to connect feagi with your webcam
Home-page: https://github.com/feagi/feagi
Author: Neuraville LLC
Author-email: info@neuraville.com
Project-URL: Bug Tracker, https://github.com/feagi/feagi/issues
Classifier: Programming Language :: Python :: 3 :: Only
Classifier: License :: OSI Approved :: Apache Software License
Classifier: Operating System :: OS Independent
Requires-Python: >=3.6
License-File: LICENSE
Requires-Dist: feagi-agent
Requires-Dist: pyzmq (>=22.3.0)
Requires-Dist: zmq (>=0.0.0) ; python_version < "3.8"
